cdft1d/__init__.py
cdft1d/cdft.py
cdft1d/cli.py
cdft1d/coulomb.py
cdft1d/diis.py
cdft1d/input.py
cdft1d/lj.py
cdft1d/plot.py
cdft1d/rad_fft.py
cdft1d/structure_factor.py
cdft1d/data/2site.smdl
cdft1d/data/input.dat
cdft1d/data/sk.data
cdft1d/data/solvent.data
cdft1d/data/spce.smdl
cdft1d-0.1.4.dist-info/METADATA
cdft1d-0.1.4.dist-info/WHEEL
cdft1d-0.1.4.dist-info/entry_points.txt
cdft1d-0.1.4.dist-info/top_level.txt
cdft1d-0.1.4.dist-info/RECORD
